icoscp_stilt/__init__.py
icoscp_stilt/const.py
icoscp_stilt/fmap.py
icoscp_stilt/py.typed
icoscp_stilt/stilt.py
icoscp_stilt/stiltobj.py
icoscp_stilt/stiltstation.py
icoscp_stilt/timefuncs.py
icoscp_stilt-0.1.3.dist-info/METADATA
icoscp_stilt-0.1.3.dist-info/WHEEL
icoscp_stilt-0.1.3.dist-info/licenses/LICENSE
icoscp_stilt-0.1.3.dist-info/RECORD
